alphafold3_pytorch/__init__.py
alphafold3_pytorch/app.py
alphafold3_pytorch/cli.py
alphafold3_pytorch/eval.py
alphafold3_pytorch/train.py
alphafold3_pytorch/common/amino_acid_constants.py
alphafold3_pytorch/common/biomolecule.py
alphafold3_pytorch/common/dna_constants.py
alphafold3_pytorch/common/ligand_constants.py
alphafold3_pytorch/common/mmcif_metadata.py
alphafold3_pytorch/common/paper_constants.py
alphafold3_pytorch/common/rna_constants.py
alphafold3_pytorch/data/__init__.py
alphafold3_pytorch/data/atom_datamodule.py
alphafold3_pytorch/data/data_pipeline.py
alphafold3_pytorch/data/kalign.py
alphafold3_pytorch/data/life.py
alphafold3_pytorch/data/mmcif_parsing.py
alphafold3_pytorch/data/mmcif_writing.py
alphafold3_pytorch/data/mocks.py
alphafold3_pytorch/data/msa_pairing.py
alphafold3_pytorch/data/msa_parsing.py
alphafold3_pytorch/data/pdb_datamodule.py
alphafold3_pytorch/data/template_parsing.py
alphafold3_pytorch/data/weighted_pdb_sampler.py
alphafold3_pytorch/data/chemical/A.cif
alphafold3_pytorch/data/chemical/ALA.cif
alphafold3_pytorch/data/chemical/ARG.cif
alphafold3_pytorch/data/chemical/ASN.cif
alphafold3_pytorch/data/chemical/ASP.cif
alphafold3_pytorch/data/chemical/C.cif
alphafold3_pytorch/data/chemical/CYS.cif
alphafold3_pytorch/data/chemical/DA.cif
alphafold3_pytorch/data/chemical/DC.cif
alphafold3_pytorch/data/chemical/DG.cif
alphafold3_pytorch/data/chemical/DT.cif
alphafold3_pytorch/data/chemical/G.cif
alphafold3_pytorch/data/chemical/GLN.cif
alphafold3_pytorch/data/chemical/GLU.cif
alphafold3_pytorch/data/chemical/GLY.cif
alphafold3_pytorch/data/chemical/HIS.cif
alphafold3_pytorch/data/chemical/ILE.cif
alphafold3_pytorch/data/chemical/LEU.cif
alphafold3_pytorch/data/chemical/LYS.cif
alphafold3_pytorch/data/chemical/MET.cif
alphafold3_pytorch/data/chemical/PHE.cif
alphafold3_pytorch/data/chemical/PRO.cif
alphafold3_pytorch/data/chemical/SER.cif
alphafold3_pytorch/data/chemical/THR.cif
alphafold3_pytorch/data/chemical/TRP.cif
alphafold3_pytorch_lightning_hydra-0.5.31.dist-info/METADATA
alphafold3_pytorch_lightning_hydra-0.5.31.dist-info/WHEEL
alphafold3_pytorch_lightning_hydra-0.5.31.dist-info/entry_points.txt
alphafold3_pytorch_lightning_hydra-0.5.31.dist-info/licenses/LICENSE
alphafold3_pytorch_lightning_hydra-0.5.31.dist-info/RECORD
