Metadata-Version: 2.3
Name: alphafold3-pytorch-lightning-hydra
Version: 0.5.31
Summary: AlphaFold 3 - Pytorch
Project-URL: Homepage, https://pypi.org/project/alphafold3-pytorch-lightning-hydra/
Project-URL: Repository, https://github.com/amorehead/alphafold3-pytorch-lightning-hydra
Author-email: Phil Wang <lucidrains@gmail.com>, Alex Morehead <alex.morehead@gmail.com>
License: MIT License
License-File: LICENSE
Keywords: artificial intelligence,deep learning,protein structure prediction
Classifier: Development Status :: 4 - Beta
Classifier: Intended Audience :: Developers
Classifier: License :: OSI Approved :: MIT License
Classifier: Programming Language :: Python :: 3.10
Classifier: Topic :: Scientific/Engineering :: Artificial Intelligence
Requires-Python: >=3.10
Requires-Dist: adam-atan2-pytorch>=0.0.8
Requires-Dist: awscliv2>=2.3.1
Requires-Dist: beartype
Requires-Dist: biopython>=1.83
Requires-Dist: click>=8.1
Requires-Dist: colt5-attention>=0.11.0
Requires-Dist: deepspeed==0.15.1
Requires-Dist: einops>=0.8.0
Requires-Dist: einx>=0.2.2
Requires-Dist: environs
Requires-Dist: fair-esm
Requires-Dist: fastapi
Requires-Dist: frame-averaging-pytorch>=0.0.18
Requires-Dist: gemmi>=0.6.6
Requires-Dist: gradio
Requires-Dist: gradio-molecule3d
Requires-Dist: huggingface-hub>=0.21.4
Requires-Dist: hydra-colorlog==1.2.0
Requires-Dist: hydra-core==1.3.2
Requires-Dist: hydra-optuna-sweeper==1.2.0
Requires-Dist: ipykernel
Requires-Dist: jaxtyping>=0.2.28
Requires-Dist: joblib
Requires-Dist: lightning>=2.4.0
Requires-Dist: lion-pytorch>=0.2.2
Requires-Dist: loguru
Requires-Dist: multimolecule
Requires-Dist: numpy==1.23.5
Requires-Dist: omegaconf
Requires-Dist: pandas>=1.5.3
Requires-Dist: pdbeccdutils==0.8.5
Requires-Dist: polars>=1.6.0
Requires-Dist: pre-commit
Requires-Dist: pydantic>=2.8.2
Requires-Dist: pytest
Requires-Dist: pyyaml
Requires-Dist: rdkit>=2024.3.5
Requires-Dist: retrying
Requires-Dist: rich
Requires-Dist: rootutils
Requires-Dist: scikit-learn>=1.5.0
Requires-Dist: scipy==1.13.1
Requires-Dist: sentencepiece
Requires-Dist: setuptools
Requires-Dist: sh>=2.0.7
Requires-Dist: shortuuid
Requires-Dist: taylor-series-linear-attention>=0.1.12
Requires-Dist: timeout-decorator>=0.5.0
Requires-Dist: torch-geometric
Requires-Dist: torch==2.3.1
Requires-Dist: torchmetrics>=1.4.1
Requires-Dist: torchtyping>=0.1.5
Requires-Dist: torchvision>=0.15.0
Requires-Dist: tqdm
Requires-Dist: transformers[torch]
Requires-Dist: wandb>=0.18.0
Provides-Extra: examples
Provides-Extra: test
Requires-Dist: pytest; extra == 'test'
Requires-Dist: pytest-shard; extra == 'test'
